[
  {
    "novelty": 0.99998939037323,
    "birth": 464,
    "survive": 156,
    "gen_bpc": 0.49895110726356506
  },
  {
    "novelty": 0.9999474287033081,
    "birth": 117,
    "survive": 451,
    "gen_bpc": 0.49660012125968933
  },
  {
    "novelty": 0.9996767044067383,
    "birth": 382,
    "survive": 390,
    "gen_bpc": 0.5029658675193787
  },
  {
    "novelty": 0.9996448755264282,
    "birth": 451,
    "survive": 10,
    "gen_bpc": 0.4913194477558136
  },
  {
    "novelty": 0.9996165037155151,
    "birth": 129,
    "survive": 216,
    "gen_bpc": 0.4951171875
  },
  {
    "novelty": 0.9996106624603271,
    "birth": 193,
    "survive": 273,
    "gen_bpc": 0.49215131998062134
  },
  {
    "novelty": 0.9995014667510986,
    "birth": 79,
    "survive": 37,
    "gen_bpc": 0.5024233460426331
  },
  {
    "novelty": 0.9994654059410095,
    "birth": 167,
    "survive": 31,
    "gen_bpc": 0.5041232705116272
  },
  {
    "novelty": 0.9993536472320557,
    "birth": 126,
    "survive": 391,
    "gen_bpc": 0.49345341324806213
  },
  {
    "novelty": 0.999309778213501,
    "birth": 459,
    "survive": 255,
    "gen_bpc": 0.5116463899612427
  },
  {
    "novelty": 0.9992652535438538,
    "birth": 242,
    "survive": 98,
    "gen_bpc": 0.49743199348449707
  },
  {
    "novelty": 0.9992396831512451,
    "birth": 58,
    "survive": 368,
    "gen_bpc": 0.5039424300193787
  },
  {
    "novelty": 0.9992140531539917,
    "birth": 424,
    "survive": 255,
    "gen_bpc": 0.5139612555503845
  },
  {
    "novelty": 0.9991934895515442,
    "birth": 453,
    "survive": 380,
    "gen_bpc": 0.5049551725387573
  },
  {
    "novelty": 0.9991694688796997,
    "birth": 451,
    "survive": 157,
    "gen_bpc": 0.5116463899612427
  },
  {
    "novelty": 0.9991475939750671,
    "birth": 175,
    "survive": 17,
    "gen_bpc": 0.5132740139961243
  },
  {
    "novelty": 0.9990478754043579,
    "birth": 376,
    "survive": 34,
    "gen_bpc": 0.5150101184844971
  },
  {
    "novelty": 0.9989547729492188,
    "birth": 114,
    "survive": 465,
    "gen_bpc": 0.5041594505310059
  },
  {
    "novelty": 0.9989531636238098,
    "birth": 118,
    "survive": 129,
    "gen_bpc": 0.5038338899612427
  },
  {
    "novelty": 0.9988805651664734,
    "birth": 1,
    "survive": 212,
    "gen_bpc": 0.484375
  },
  {
    "novelty": 0.9988476634025574,
    "birth": 386,
    "survive": 58,
    "gen_bpc": 0.4830729067325592
  },
  {
    "novelty": 0.9987662434577942,
    "birth": 439,
    "survive": 11,
    "gen_bpc": 0.4919704794883728
  },
  {
    "novelty": 0.998693585395813,
    "birth": 373,
    "survive": 194,
    "gen_bpc": 0.5012297630310059
  },
  {
    "novelty": 0.9986011981964111,
    "birth": 453,
    "survive": 381,
    "gen_bpc": 0.5183376669883728
  },
  {
    "novelty": 0.9985451102256775,
    "birth": 383,
    "survive": 391,
    "gen_bpc": 0.5059317350387573
  },
  {
    "novelty": 0.9985395669937134,
    "birth": 459,
    "survive": 252,
    "gen_bpc": 0.4812282919883728
  },
  {
    "novelty": 0.998528003692627,
    "birth": 159,
    "survive": 111,
    "gen_bpc": 0.48885995149612427
  },
  {
    "novelty": 0.9985150098800659,
    "birth": 283,
    "survive": 485,
    "gen_bpc": 0.48108363151550293
  },
  {
    "novelty": 0.9981416463851929,
    "birth": 31,
    "survive": 91,
    "gen_bpc": 0.5198567509651184
  },
  {
    "novelty": 0.9980922341346741,
    "birth": 317,
    "survive": 133,
    "gen_bpc": 0.5209780335426331
  },
  {
    "novelty": 0.9978724122047424,
    "birth": 223,
    "survive": 257,
    "gen_bpc": 0.49764901399612427
  },
  {
    "novelty": 0.9978674054145813,
    "birth": 46,
    "survive": 374,
    "gen_bpc": 0.5026041865348816
  },
  {
    "novelty": 0.9977381825447083,
    "birth": 118,
    "survive": 32,
    "gen_bpc": 0.49374276399612427
  },
  {
    "novelty": 0.9976915121078491,
    "birth": 317,
    "survive": 135,
    "gen_bpc": 0.5124782919883728
  },
  {
    "novelty": 0.9976191520690918,
    "birth": 15,
    "survive": 77,
    "gen_bpc": 0.5236545205116272
  },
  {
    "novelty": 0.9974397420883179,
    "birth": 298,
    "survive": 123,
    "gen_bpc": 0.4984809160232544
  },
  {
    "novelty": 0.9974309802055359,
    "birth": 284,
    "survive": 317,
    "gen_bpc": 0.5229311585426331
  },
  {
    "novelty": 0.9971612095832825,
    "birth": 505,
    "survive": 96,
    "gen_bpc": 0.47847944498062134
  },
  {
    "novelty": 0.9970688819885254,
    "birth": 118,
    "survive": 417,
    "gen_bpc": 0.47359663248062134
  },
  {
    "novelty": 0.9970604181289673,
    "birth": 374,
    "survive": 128,
    "gen_bpc": 0.5268735289573669
  },
  {
    "novelty": 0.9970487356185913,
    "birth": 449,
    "survive": 98,
    "gen_bpc": 0.5177951455116272
  },
  {
    "novelty": 0.9968342185020447,
    "birth": 375,
    "survive": 26,
    "gen_bpc": 0.49540653824806213
  },
  {
    "novelty": 0.9965677261352539,
    "birth": 223,
    "survive": 36,
    "gen_bpc": 0.5096571445465088
  },
  {
    "novelty": 0.9964278936386108,
    "birth": 392,
    "survive": 123,
    "gen_bpc": 0.47034144401550293
  },
  {
    "novelty": 0.996397852897644,
    "birth": 321,
    "survive": 290,
    "gen_bpc": 0.5219907164573669
  },
  {
    "novelty": 0.9963815808296204,
    "birth": 296,
    "survive": 147,
    "gen_bpc": 0.5008319020271301
  },
  {
    "novelty": 0.9963675141334534,
    "birth": 114,
    "survive": 466,
    "gen_bpc": 0.5281394720077515
  },
  {
    "novelty": 0.9962937831878662,
    "birth": 243,
    "survive": 419,
    "gen_bpc": 0.48748552799224854
  },
  {
    "novelty": 0.9962095618247986,
    "birth": 502,
    "survive": 34,
    "gen_bpc": 0.5206524729728699
  },
  {
    "novelty": 0.9960465431213379,
    "birth": 1,
    "survive": 84,
    "gen_bpc": 0.5285373330116272
  },
  {
    "novelty": 0.9960451722145081,
    "birth": 242,
    "survive": 193,
    "gen_bpc": 0.5186270475387573
  },
  {
    "novelty": 0.9960062503814697,
    "birth": 422,
    "survive": 255,
    "gen_bpc": 0.5152994990348816
  },
  {
    "novelty": 0.9959423542022705,
    "birth": 52,
    "survive": 481,
    "gen_bpc": 0.46817129850387573
  },
  {
    "novelty": 0.9958639144897461,
    "birth": 455,
    "survive": 381,
    "gen_bpc": 0.5280671119689941
  },
  {
    "novelty": 0.9957053661346436,
    "birth": 87,
    "survive": 26,
    "gen_bpc": 0.5044125914573669
  },
  {
    "novelty": 0.995689868927002,
    "birth": 507,
    "survive": 34,
    "gen_bpc": 0.5328052639961243
  },
  {
    "novelty": 0.9956434369087219,
    "birth": 31,
    "survive": 90,
    "gen_bpc": 0.48658129572868347
  },
  {
    "novelty": 0.9952954053878784,
    "birth": 460,
    "survive": 251,
    "gen_bpc": 0.5165292024612427
  },
  {
    "novelty": 0.9951998591423035,
    "birth": 31,
    "survive": 92,
    "gen_bpc": 0.5279224514961243
  },
  {
    "novelty": 0.9949690699577332,
    "birth": 268,
    "survive": 110,
    "gen_bpc": 0.5354456305503845
  },
  {
    "novelty": 0.9949076175689697,
    "birth": 129,
    "survive": 88,
    "gen_bpc": 0.4809027910232544
  },
  {
    "novelty": 0.9946860671043396,
    "birth": 376,
    "survive": 291,
    "gen_bpc": 0.47377750277519226
  },
  {
    "novelty": 0.9944237470626831,
    "birth": 35,
    "survive": 495,
    "gen_bpc": 0.5021701455116272
  },
  {
    "novelty": 0.9944066405296326,
    "birth": 381,
    "survive": 391,
    "gen_bpc": 0.49866175651550293
  },
  {
    "novelty": 0.9943980574607849,
    "birth": 34,
    "survive": 494,
    "gen_bpc": 0.5252459645271301
  },
  {
    "novelty": 0.9943712949752808,
    "birth": 27,
    "survive": 12,
    "gen_bpc": 0.5365668535232544
  },
  {
    "novelty": 0.9942106604576111,
    "birth": 43,
    "survive": 11,
    "gen_bpc": 0.4635416567325592
  },
  {
    "novelty": 0.9941325783729553,
    "birth": 112,
    "survive": 359,
    "gen_bpc": 0.5378327369689941
  },
  {
    "novelty": 0.9939553141593933,
    "birth": 188,
    "survive": 241,
    "gen_bpc": 0.46205875277519226
  },
  {
    "novelty": 0.9939113855361938,
    "birth": 271,
    "survive": 441,
    "gen_bpc": 0.4619140625
  },
  {
    "novelty": 0.9938222765922546,
    "birth": 189,
    "survive": 6,
    "gen_bpc": 0.5392795205116272
  },
  {
    "novelty": 0.9937864542007446,
    "birth": 120,
    "survive": 34,
    "gen_bpc": 0.46075665950775146
  },
  {
    "novelty": 0.9937787652015686,
    "birth": 137,
    "survive": 120,
    "gen_bpc": 0.4649522602558136
  },
  {
    "novelty": 0.9936650991439819,
    "birth": 168,
    "survive": 147,
    "gen_bpc": 0.5031105279922485
  },
  {
    "novelty": 0.9935297966003418,
    "birth": 415,
    "survive": 78,
    "gen_bpc": 0.5060040354728699
  },
  {
    "novelty": 0.9934660196304321,
    "birth": 10,
    "survive": 284,
    "gen_bpc": 0.4704861044883728
  },
  {
    "novelty": 0.9933652281761169,
    "birth": 407,
    "survive": 27,
    "gen_bpc": 0.5364944934844971
  },
  {
    "novelty": 0.99335777759552,
    "birth": 419,
    "survive": 5,
    "gen_bpc": 0.46238425374031067
  },
  {
    "novelty": 0.9933328628540039,
    "birth": 286,
    "survive": 319,
    "gen_bpc": 0.4903428852558136
  },
  {
    "novelty": 0.9932276010513306,
    "birth": 262,
    "survive": 502,
    "gen_bpc": 0.5397135615348816
  },
  {
    "novelty": 0.9932030439376831,
    "birth": 451,
    "survive": 221,
    "gen_bpc": 0.4596354067325592
  },
  {
    "novelty": 0.9931381344795227,
    "birth": 399,
    "survive": 33,
    "gen_bpc": 0.46166089177131653
  },
  {
    "novelty": 0.9931024312973022,
    "birth": 304,
    "survive": 55,
    "gen_bpc": 0.48184317350387573
  },
  {
    "novelty": 0.9930919408798218,
    "birth": 48,
    "survive": 471,
    "gen_bpc": 0.4817708432674408
  },
  {
    "novelty": 0.9930793046951294,
    "birth": 223,
    "survive": 42,
    "gen_bpc": 0.45927372574806213
  },
  {
    "novelty": 0.9930490851402283,
    "birth": 449,
    "survive": 244,
    "gen_bpc": 0.4771050214767456
  },
  {
    "novelty": 0.992993950843811,
    "birth": 456,
    "survive": 248,
    "gen_bpc": 0.5388454794883728
  },
  {
    "novelty": 0.9928681254386902,
    "birth": 395,
    "survive": 7,
    "gen_bpc": 0.5035807490348816
  },
  {
    "novelty": 0.9927775859832764,
    "birth": 262,
    "survive": 313,
    "gen_bpc": 0.5059678554534912
  },
  {
    "novelty": 0.9927651286125183,
    "birth": 245,
    "survive": 291,
    "gen_bpc": 0.5055338740348816
  },
  {
    "novelty": 0.9927559494972229,
    "birth": 498,
    "survive": 193,
    "gen_bpc": 0.5244502425193787
  },
  {
    "novelty": 0.9923874139785767,
    "birth": 119,
    "survive": 195,
    "gen_bpc": 0.5112124085426331
  },
  {
    "novelty": 0.9923591613769531,
    "birth": 380,
    "survive": 390,
    "gen_bpc": 0.46133536100387573
  },
  {
    "novelty": 0.9923052191734314,
    "birth": 462,
    "survive": 268,
    "gen_bpc": 0.4680989682674408
  },
  {
    "novelty": 0.992101788520813,
    "birth": 34,
    "survive": 327,
    "gen_bpc": 0.45688655972480774
  },
  {
    "novelty": 0.992088258266449,
    "birth": 101,
    "survive": 472,
    "gen_bpc": 0.5004340410232544
  },
  {
    "novelty": 0.9920218586921692,
    "birth": 94,
    "survive": 477,
    "gen_bpc": 0.5147569179534912
  },
  {
    "novelty": 0.9919178485870361,
    "birth": 34,
    "survive": 240,
    "gen_bpc": 0.5411602854728699
  },
  {
    "novelty": 0.9918872714042664,
    "birth": 68,
    "survive": 30,
    "gen_bpc": 0.45576533675193787
  },
  {
    "novelty": 0.9918574690818787,
    "birth": 465,
    "survive": 252,
    "gen_bpc": 0.5070529580116272
  },
  {
    "novelty": 0.991714596748352,
    "birth": 283,
    "survive": 23,
    "gen_bpc": 0.5441985130310059
  },
  {
    "novelty": 0.9916872382164001,
    "birth": 417,
    "survive": 479,
    "gen_bpc": 0.4776475727558136
  },
  {
    "novelty": 0.9915757775306702,
    "birth": 97,
    "survive": 238,
    "gen_bpc": 0.5366753339767456
  },
  {
    "novelty": 0.9911136627197266,
    "birth": 215,
    "survive": 12,
    "gen_bpc": 0.5040147304534912
  },
  {
    "novelty": 0.991036057472229,
    "birth": 118,
    "survive": 451,
    "gen_bpc": 0.48397713899612427
  },
  {
    "novelty": 0.9909850358963013,
    "birth": 118,
    "survive": 195,
    "gen_bpc": 0.5218822360038757
  },
  {
    "novelty": 0.9908437728881836,
    "birth": 92,
    "survive": 477,
    "gen_bpc": 0.5452112555503845
  },
  {
    "novelty": 0.9908050298690796,
    "birth": 97,
    "survive": 93,
    "gen_bpc": 0.45558449625968933
  },
  {
    "novelty": 0.990655779838562,
    "birth": 47,
    "survive": 43,
    "gen_bpc": 0.4761284589767456
  },
  {
    "novelty": 0.9905517101287842,
    "birth": 111,
    "survive": 469,
    "gen_bpc": 0.5244140625
  },
  {
    "novelty": 0.9903298616409302,
    "birth": 496,
    "survive": 423,
    "gen_bpc": 0.45641636848449707
  },
  {
    "novelty": 0.9903184771537781,
    "birth": 121,
    "survive": 35,
    "gen_bpc": 0.5211226940155029
  },
  {
    "novelty": 0.9903154969215393,
    "birth": 35,
    "survive": 493,
    "gen_bpc": 0.46303531527519226
  },
  {
    "novelty": 0.9902971386909485,
    "birth": 50,
    "survive": 482,
    "gen_bpc": 0.5149016380310059
  },
  {
    "novelty": 0.9902926683425903,
    "birth": 237,
    "survive": 249,
    "gen_bpc": 0.49974682927131653
  },
  {
    "novelty": 0.9902868866920471,
    "birth": 315,
    "survive": 13,
    "gen_bpc": 0.4708116352558136
  },
  {
    "novelty": 0.9902397394180298,
    "birth": 144,
    "survive": 46,
    "gen_bpc": 0.4507378339767456
  },
  {
    "novelty": 0.9902063012123108,
    "birth": 392,
    "survive": 267,
    "gen_bpc": 0.5035083889961243
  },
  {
    "novelty": 0.9901412129402161,
    "birth": 198,
    "survive": 382,
    "gen_bpc": 0.4838324785232544
  },
  {
    "novelty": 0.9900841116905212,
    "birth": 277,
    "survive": 493,
    "gen_bpc": 0.5442346930503845
  },
  {
    "novelty": 0.9900436401367188,
    "birth": 116,
    "survive": 450,
    "gen_bpc": 0.5073061585426331
  },
  {
    "novelty": 0.9900352358818054,
    "birth": 239,
    "survive": 45,
    "gen_bpc": 0.4544270932674408
  },
  {
    "novelty": 0.9899251461029053,
    "birth": 382,
    "survive": 388,
    "gen_bpc": 0.47269243001937866
  },
  {
    "novelty": 0.9899101257324219,
    "birth": 55,
    "survive": 21,
    "gen_bpc": 0.4906684160232544
  },
  {
    "novelty": 0.9898702502250671,
    "birth": 49,
    "survive": 483,
    "gen_bpc": 0.45641636848449707
  },
  {
    "novelty": 0.9898480176925659,
    "birth": 377,
    "survive": 290,
    "gen_bpc": 0.45211225748062134
  },
  {
    "novelty": 0.9898479580879211,
    "birth": 226,
    "survive": 399,
    "gen_bpc": 0.4614800214767456
  },
  {
    "novelty": 0.9898034930229187,
    "birth": 79,
    "survive": 39,
    "gen_bpc": 0.46133536100387573
  },
  {
    "novelty": 0.9897277355194092,
    "birth": 8,
    "survive": 139,
    "gen_bpc": 0.48846209049224854
  },
  {
    "novelty": 0.9897238612174988,
    "birth": 177,
    "survive": 245,
    "gen_bpc": 0.4493272602558136
  },
  {
    "novelty": 0.9897164106369019,
    "birth": 444,
    "survive": 131,
    "gen_bpc": 0.5390263199806213
  },
  {
    "novelty": 0.9896676540374756,
    "birth": 114,
    "survive": 467,
    "gen_bpc": 0.46813511848449707
  },
  {
    "novelty": 0.9895418286323547,
    "birth": 87,
    "survive": 23,
    "gen_bpc": 0.5134186744689941
  },
  {
    "novelty": 0.9894817471504211,
    "birth": 374,
    "survive": 193,
    "gen_bpc": 0.5446324944496155
  },
  {
    "novelty": 0.9893397092819214,
    "birth": 125,
    "survive": 132,
    "gen_bpc": 0.5381582975387573
  },
  {
    "novelty": 0.9893261790275574,
    "birth": 61,
    "survive": 133,
    "gen_bpc": 0.47377750277519226
  },
  {
    "novelty": 0.9893226027488708,
    "birth": 136,
    "survive": 11,
    "gen_bpc": 0.5010489225387573
  },
  {
    "novelty": 0.9893225431442261,
    "birth": 407,
    "survive": 20,
    "gen_bpc": 0.5264033675193787
  },
  {
    "novelty": 0.9893075227737427,
    "birth": 159,
    "survive": 79,
    "gen_bpc": 0.5300202369689941
  },
  {
    "novelty": 0.9892484545707703,
    "birth": 374,
    "survive": 320,
    "gen_bpc": 0.5422453880310059
  },
  {
    "novelty": 0.9892454147338867,
    "birth": 449,
    "survive": 290,
    "gen_bpc": 0.5032551884651184
  },
  {
    "novelty": 0.9892128109931946,
    "birth": 283,
    "survive": 484,
    "gen_bpc": 0.5477792024612427
  },
  {
    "novelty": 0.9891558289527893,
    "birth": 385,
    "survive": 216,
    "gen_bpc": 0.5478877425193787
  },
  {
    "novelty": 0.9889874458312988,
    "birth": 303,
    "survive": 42,
    "gen_bpc": 0.5445963740348816
  },
  {
    "novelty": 0.9889088869094849,
    "birth": 195,
    "survive": 315,
    "gen_bpc": 0.5316478610038757
  },
  {
    "novelty": 0.9888980984687805,
    "birth": 422,
    "survive": 253,
    "gen_bpc": 0.47164350748062134
  },
  {
    "novelty": 0.9888913631439209,
    "birth": 239,
    "survive": 44,
    "gen_bpc": 0.5185546875
  },
  {
    "novelty": 0.9886125922203064,
    "birth": 283,
    "survive": 9,
    "gen_bpc": 0.5328052639961243
  },
  {
    "novelty": 0.9885761737823486,
    "birth": 283,
    "survive": 487,
    "gen_bpc": 0.44722944498062134
  },
  {
    "novelty": 0.988563597202301,
    "birth": 5,
    "survive": 183,
    "gen_bpc": 0.5138888955116272
  },
  {
    "novelty": 0.9885172247886658,
    "birth": 96,
    "survive": 124,
    "gen_bpc": 0.5260778069496155
  },
  {
    "novelty": 0.9884856939315796,
    "birth": 359,
    "survive": 8,
    "gen_bpc": 0.5460430979728699
  },
  {
    "novelty": 0.9884622097015381,
    "birth": 451,
    "survive": 412,
    "gen_bpc": 0.5486111044883728
  },
  {
    "novelty": 0.988316535949707,
    "birth": 183,
    "survive": 26,
    "gen_bpc": 0.5392433404922485
  },
  {
    "novelty": 0.988282322883606,
    "birth": 151,
    "survive": 38,
    "gen_bpc": 0.44751879572868347
  },
  {
    "novelty": 0.9881731867790222,
    "birth": 176,
    "survive": 215,
    "gen_bpc": 0.5050636529922485
  },
  {
    "novelty": 0.9881386160850525,
    "birth": 457,
    "survive": 253,
    "gen_bpc": 0.5533854365348816
  },
  {
    "novelty": 0.9881097674369812,
    "birth": 195,
    "survive": 12,
    "gen_bpc": 0.5470558404922485
  },
  {
    "novelty": 0.9880384802818298,
    "birth": 353,
    "survive": 62,
    "gen_bpc": 0.4650607705116272
  },
  {
    "novelty": 0.9880159497261047,
    "birth": 52,
    "survive": 480,
    "gen_bpc": 0.44527631998062134
  },
  {
    "novelty": 0.9880034327507019,
    "birth": 62,
    "survive": 122,
    "gen_bpc": 0.4819878339767456
  },
  {
    "novelty": 0.9879151582717896,
    "birth": 44,
    "survive": 483,
    "gen_bpc": 0.44665074348449707
  },
  {
    "novelty": 0.9876293540000916,
    "birth": 296,
    "survive": 403,
    "gen_bpc": 0.5364944934844971
  },
  {
    "novelty": 0.9876202940940857,
    "birth": 21,
    "survive": 118,
    "gen_bpc": 0.45858651399612427
  },
  {
    "novelty": 0.987608015537262,
    "birth": 422,
    "survive": 252,
    "gen_bpc": 0.48661747574806213
  },
  {
    "novelty": 0.9874346256256104,
    "birth": 257,
    "survive": 436,
    "gen_bpc": 0.48542389273643494
  },
  {
    "novelty": 0.9874125719070435,
    "birth": 27,
    "survive": 0,
    "gen_bpc": 0.4691840410232544
  },
  {
    "novelty": 0.9873376488685608,
    "birth": 119,
    "survive": 129,
    "gen_bpc": 0.5552300214767456
  },
  {
    "novelty": 0.9872412085533142,
    "birth": 196,
    "survive": 63,
    "gen_bpc": 0.4507378339767456
  },
  {
    "novelty": 0.9872334599494934,
    "birth": 359,
    "survive": 9,
    "gen_bpc": 0.44939959049224854
  },
  {
    "novelty": 0.9870771169662476,
    "birth": 19,
    "survive": 13,
    "gen_bpc": 0.45500579476356506
  },
  {
    "novelty": 0.9870292544364929,
    "birth": 367,
    "survive": 22,
    "gen_bpc": 0.44524016976356506
  },
  {
    "novelty": 0.9868736267089844,
    "birth": 124,
    "survive": 132,
    "gen_bpc": 0.5569661259651184
  },
  {
    "novelty": 0.9868693947792053,
    "birth": 168,
    "survive": 19,
    "gen_bpc": 0.5249204039573669
  },
  {
    "novelty": 0.9867385029792786,
    "birth": 237,
    "survive": 251,
    "gen_bpc": 0.4453125
  },
  {
    "novelty": 0.9865863919258118,
    "birth": 105,
    "survive": 471,
    "gen_bpc": 0.5399305820465088
  },
  {
    "novelty": 0.9864645004272461,
    "birth": 423,
    "survive": 18,
    "gen_bpc": 0.4418402910232544
  },
  {
    "novelty": 0.9861822128295898,
    "birth": 311,
    "survive": 24,
    "gen_bpc": 0.44806134700775146
  },
  {
    "novelty": 0.9861567616462708,
    "birth": 498,
    "survive": 419,
    "gen_bpc": 0.44939959049224854
  },
  {
    "novelty": 0.98614501953125,
    "birth": 456,
    "survive": 254,
    "gen_bpc": 0.5019169449806213
  },
  {
    "novelty": 0.9861088991165161,
    "birth": 208,
    "survive": 412,
    "gen_bpc": 0.5533130764961243
  },
  {
    "novelty": 0.9859805703163147,
    "birth": 190,
    "survive": 130,
    "gen_bpc": 0.5362051725387573
  },
  {
    "novelty": 0.985821545124054,
    "birth": 317,
    "survive": 132,
    "gen_bpc": 0.45352286100387573
  },
  {
    "novelty": 0.9857866764068604,
    "birth": 225,
    "survive": 63,
    "gen_bpc": 0.4516059160232544
  },
  {
    "novelty": 0.9857829809188843,
    "birth": 130,
    "survive": 56,
    "gen_bpc": 0.5596064925193787
  },
  {
    "novelty": 0.9857335090637207,
    "birth": 303,
    "survive": 44,
    "gen_bpc": 0.5425347089767456
  },
  {
    "novelty": 0.9857136011123657,
    "birth": 126,
    "survive": 390,
    "gen_bpc": 0.4893663227558136
  },
  {
    "novelty": 0.9856630563735962,
    "birth": 400,
    "survive": 174,
    "gen_bpc": 0.44158709049224854
  },
  {
    "novelty": 0.9855343699455261,
    "birth": 272,
    "survive": 58,
    "gen_bpc": 0.5591724514961243
  },
  {
    "novelty": 0.9855168461799622,
    "birth": 304,
    "survive": 334,
    "gen_bpc": 0.46209490299224854
  },
  {
    "novelty": 0.9854622483253479,
    "birth": 271,
    "survive": 111,
    "gen_bpc": 0.44419124722480774
  },
  {
    "novelty": 0.9853452444076538,
    "birth": 262,
    "survive": 498,
    "gen_bpc": 0.5317202210426331
  },
  {
    "novelty": 0.98516845703125,
    "birth": 257,
    "survive": 84,
    "gen_bpc": 0.5280309319496155
  },
  {
    "novelty": 0.9850384593009949,
    "birth": 303,
    "survive": 35,
    "gen_bpc": 0.5557725429534912
  },
  {
    "novelty": 0.9848805069923401,
    "birth": 511,
    "survive": 276,
    "gen_bpc": 0.49529802799224854
  },
  {
    "novelty": 0.9848560690879822,
    "birth": 415,
    "survive": 36,
    "gen_bpc": 0.5612340569496155
  },
  {
    "novelty": 0.9848223924636841,
    "birth": 136,
    "survive": 371,
    "gen_bpc": 0.5069805979728699
  },
  {
    "novelty": 0.9848122000694275,
    "birth": 453,
    "survive": 383,
    "gen_bpc": 0.44751879572868347
  },
  {
    "novelty": 0.9845064878463745,
    "birth": 67,
    "survive": 18,
    "gen_bpc": 0.5613064169883728
  },
  {
    "novelty": 0.9843087196350098,
    "birth": 457,
    "survive": 250,
    "gen_bpc": 0.5133824944496155
  }
]