{
  "radius": 2,
  "k": 5,
  "W": 64,
  "T": 64,
  "batch": 8192,
  "keep": 2048,
  "steps": 32,
  "warm": 6,
  "n_residual": 680,
  "results": [
    {
      "rule": 4259958114,
      "lp": 4.411691665649414,
      "bpc_warm": 4.9087815284729,
      "bpc_end": 0.49708986282348633,
      "nl": 10,
      "period": 0,
      "density": 0.871337890625,
      "damage": 0.0625
    },
    {
      "rule": 3512896128,
      "lp": 1.9317972660064697,
      "bpc_warm": 2.438082695007324,
      "bpc_end": 0.5062854290008545,
      "nl": 11,
      "period": 0,
      "density": 0.09033203125,
      "damage": 0.03125
    },
    {
      "rule": 2663599680,
      "lp": 1.13142728805542,
      "bpc_warm": 2.1504831314086914,
      "bpc_end": 1.0190558433532715,
      "nl": 10,
      "period": 0,
      "density": 0.427978515625,
      "damage": 0.265625
    },
    {
      "rule": 2981656613,
      "lp": 1.0318094491958618,
      "bpc_warm": 1.1532825231552124,
      "bpc_end": 0.12147302180528641,
      "nl": 9,
      "period": 0,
      "density": 0.4599609375,
      "damage": 0.0625
    },
    {
      "rule": 533284828,
      "lp": 1.0105823278427124,
      "bpc_warm": 1.5357794761657715,
      "bpc_end": 0.5251971483230591,
      "nl": 10,
      "period": 0,
      "density": 0.5361328125,
      "damage": 0.15625
    },
    {
      "rule": 4059076994,
      "lp": 0.9724636673927307,
      "bpc_warm": 1.1900641918182373,
      "bpc_end": 0.2176005244255066,
      "nl": 9,
      "period": 0,
      "density": 0.79931640625,
      "damage": 0.046875
    },
    {
      "rule": 4158754070,
      "lp": 0.9680345058441162,
      "bpc_warm": 1.5420339107513428,
      "bpc_end": 0.5739994049072266,
      "nl": 10,
      "period": 0,
      "density": 0.91796875,
      "damage": 0.203125
    },
    {
      "rule": 4240807781,
      "lp": 0.9603819251060486,
      "bpc_warm": 1.5382142066955566,
      "bpc_end": 0.5778322815895081,
      "nl": 11,
      "period": 0,
      "density": 0.652587890625,
      "damage": 0.109375
    },
    {
      "rule": 3940664392,
      "lp": 0.9129777550697327,
      "bpc_warm": 1.0577009916305542,
      "bpc_end": 0.14472322165966034,
      "nl": 10,
      "period": 0,
      "density": 0.14208984375,
      "damage": 0.125
    },
    {
      "rule": 2126646922,
      "lp": 0.9054279923439026,
      "bpc_warm": 1.091003179550171,
      "bpc_end": 0.1855751872062683,
      "nl": 9,
      "period": 0,
      "density": 0.366455078125,
      "damage": 0.03125
    },
    {
      "rule": 7913454,
      "lp": 0.8310755491256714,
      "bpc_warm": 1.046634316444397,
      "bpc_end": 0.2155587524175644,
      "nl": 7,
      "period": 0,
      "density": 0.43798828125,
      "damage": 0.21875
    },
    {
      "rule": 854434796,
      "lp": 0.7966266870498657,
      "bpc_warm": 0.9791072607040405,
      "bpc_end": 0.1824805736541748,
      "nl": 6,
      "period": 0,
      "density": 0.517333984375,
      "damage": 0.03125
    },
    {
      "rule": 299397154,
      "lp": 0.7644500732421875,
      "bpc_warm": 0.9226059317588806,
      "bpc_end": 0.15815584361553192,
      "nl": 9,
      "period": 0,
      "density": 0.20361328125,
      "damage": 0.15625
    },
    {
      "rule": 899562803,
      "lp": 0.7418516278266907,
      "bpc_warm": 0.8584511280059814,
      "bpc_end": 0.11659949272871017,
      "nl": 10,
      "period": 0,
      "density": 0.568359375,
      "damage": 0.0625
    },
    {
      "rule": 2763178431,
      "lp": 0.7276312112808228,
      "bpc_warm": 0.9634653925895691,
      "bpc_end": 0.23583421111106873,
      "nl": 11,
      "period": 0,
      "density": 0.605712890625,
      "damage": 0.046875
    },
    {
      "rule": 157999666,
      "lp": 0.716764509677887,
      "bpc_warm": 0.8764196038246155,
      "bpc_end": 0.15965507924556732,
      "nl": 11,
      "period": 0,
      "density": 0.5,
      "damage": 0.375
    },
    {
      "rule": 730053123,
      "lp": 0.7166240811347961,
      "bpc_warm": 0.8584453463554382,
      "bpc_end": 0.1418212503194809,
      "nl": 10,
      "period": 0,
      "density": 0.3662109375,
      "damage": 0.390625
    },
    {
      "rule": 3147608525,
      "lp": 0.7162686586380005,
      "bpc_warm": 0.9327308535575867,
      "bpc_end": 0.21646219491958618,
      "nl": 7,
      "period": 0,
      "density": 0.6572265625,
      "damage": 0.171875
    },
    {
      "rule": 3695768777,
      "lp": 0.7029505968093872,
      "bpc_warm": 0.8233062028884888,
      "bpc_end": 0.12035559862852097,
      "nl": 8,
      "period": 0,
      "density": 0.654296875,
      "damage": 0.390625
    },
    {
      "rule": 4122877180,
      "lp": 0.6987577676773071,
      "bpc_warm": 0.9580329656600952,
      "bpc_end": 0.2592752277851105,
      "nl": 9,
      "period": 0,
      "density": 0.665771484375,
      "damage": 0.3125
    },
    {
      "rule": 4225642192,
      "lp": 0.6916241645812988,
      "bpc_warm": 0.9293102025985718,
      "bpc_end": 0.23768606781959534,
      "nl": 10,
      "period": 0,
      "density": 0.567626953125,
      "damage": 0.046875
    },
    {
      "rule": 2286553151,
      "lp": 0.6912362575531006,
      "bpc_warm": 0.8844485282897949,
      "bpc_end": 0.19321230053901672,
      "nl": 10,
      "period": 0,
      "density": 0.3701171875,
      "damage": 0.03125
    },
    {
      "rule": 3671558653,
      "lp": 0.6866681575775146,
      "bpc_warm": 0.9214035868644714,
      "bpc_end": 0.2347353994846344,
      "nl": 11,
      "period": 0,
      "density": 0.74951171875,
      "damage": 0.046875
    },
    {
      "rule": 2121139673,
      "lp": 0.677406907081604,
      "bpc_warm": 0.9540669322013855,
      "bpc_end": 0.2766600251197815,
      "nl": 8,
      "period": 0,
      "density": 0.603271484375,
      "damage": 0.03125
    }
  ]
}